date_tree/__init__.py
date_tree/_add_dates.py
date_tree/_date_exists.py
date_tree/_days_of_week.py
date_tree/_delete_dates.py
date_tree/_filter_dates.py
date_tree/_helper_methods.py
date_tree/_show_dates.py
date_tree/date_tree.py
date_tree-1.0.2.dist-info/licenses/LICENSE
date_tree-1.0.2.dist-info/METADATA
date_tree-1.0.2.dist-info/WHEEL
date_tree-1.0.2.dist-info/top_level.txt
date_tree-1.0.2.dist-info/RECORD
