Metadata-Version: 2.4
Name: date-tree
Version: 1.0.2
Summary: Tree-based date filtering utilities
Author: Drew Hill
License: MIT
Requires-Python: >=3.10
License-File: LICENSE
Requires-Dist: bintrees
Dynamic: license-file
